pyscraping/PyScraping.py
pyscraping/__init__.py
pyscraping-1.0.5.dist-info/LICENSE
pyscraping-1.0.5.dist-info/METADATA
pyscraping-1.0.5.dist-info/WHEEL
pyscraping-1.0.5.dist-info/top_level.txt
pyscraping-1.0.5.dist-info/RECORD
