Metadata-Version: 2.1
Name: pyscraping
Version: 1.0.5
Summary: PyScraping is a universal web-scraping util for Python, built with simplicity in mind.
Home-page: https://github.com/riodev99/pyscraping
Author: riodev99
Author-email: jgeniya1994@gmail.com
Project-URL: Source, https://github.com/riodev99/pyscraping
Classifier: Development Status :: 3 - Alpha
Classifier: Intended Audience :: Developers
Classifier: License :: OSI Approved :: MIT License
Classifier: Programming Language :: Python :: 3
Classifier: Programming Language :: Python :: 3.6
Classifier: Programming Language :: Python :: 3.7
Classifier: Programming Language :: Python :: 3.8
Classifier: Programming Language :: Python :: 3.9
Classifier: Programming Language :: Python :: 3.10
Classifier: Programming Language :: Python :: 3.11
Requires-Python: >=3.6
License-File: LICENSE
Requires-Dist: requests
Requires-Dist: bs4
